arctic_training_cli.py
arctic_training/__init__.py
arctic_training/debug.py
arctic_training/entrypoint.py
arctic_training/exceptions.py
arctic_training/logging.py
arctic_training/metrics.py
arctic_training/monkey_patches.py
arctic_training/registry.py
arctic_training/testing_utils.py
arctic_training/utils.py
arctic_training/callback/__init__.py
arctic_training/callback/callback.py
arctic_training/callback/logging.py
arctic_training/callback/mixin.py
arctic_training/checkpoint/__init__.py
arctic_training/checkpoint/ds_engine.py
arctic_training/checkpoint/engine.py
arctic_training/checkpoint/hf_engine.py
arctic_training/config/__init__.py
arctic_training/config/base.py
arctic_training/config/checkpoint.py
arctic_training/config/data.py
arctic_training/config/enums.py
arctic_training/config/logger.py
arctic_training/config/model.py
arctic_training/config/optimizer.py
arctic_training/config/scheduler.py
arctic_training/config/tokenizer.py
arctic_training/config/trainer.py
arctic_training/config/utils.py
arctic_training/config/wandb.py
arctic_training/data/__init__.py
arctic_training/data/causal_factory.py
arctic_training/data/dpo_factory.py
arctic_training/data/factory.py
arctic_training/data/hf_causal_source.py
arctic_training/data/hf_instruct_source.py
arctic_training/data/hf_source.py
arctic_training/data/sft_factory.py
arctic_training/data/snowflake_source.py
arctic_training/data/source.py
arctic_training/data/utils.py
arctic_training/launcher/ray_launcher.py
arctic_training/model/__init__.py
arctic_training/model/factory.py
arctic_training/model/hf_factory.py
arctic_training/model/liger_factory.py
arctic_training/model/tiled_compute.py
arctic_training/optimizer/__init__.py
arctic_training/optimizer/adam_factory.py
arctic_training/optimizer/factory.py
arctic_training/scheduler/__init__.py
arctic_training/scheduler/factory.py
arctic_training/scheduler/hf_factory.py
arctic_training/scheduler/wsd_factory.py
arctic_training/synth/README.md
arctic_training-0.7.1.dist-info/METADATA
arctic_training-0.7.1.dist-info/WHEEL
arctic_training-0.7.1.dist-info/entry_points.txt
arctic_training-0.7.1.dist-info/licenses/LICENSE
arctic_training-0.7.1.dist-info/RECORD
