Metadata-Version: 2.4
Name: arctic_training
Version: 0.7.1
Summary: Snowflake LLM training library
Project-URL: Homepage, https://github.com/snowflakedb/ArcticTraining
Project-URL: Issues, https://github.com/snowflakedb/ArcticTraining/issues
Author-email: michael.wyatt@snowflake.com, stas.bekman@snowflake.com, jeff.rasley@snowflake.com, zhewei.yao@snowflake.com, samyam.rajbhandari@snowflake.com, aurick.qiao@snowflake.com, canwen.xu@snowflake.com
License-Expression: Apache-2.0
License-File: LICENSE
Keywords: llm,training
Classifier: Development Status :: 4 - Beta
Classifier: Programming Language :: Python :: 3
Classifier: Programming Language :: Python :: 3.10
Classifier: Programming Language :: Python :: 3.11
Classifier: Programming Language :: Python :: 3.12
Requires-Python: >=3.8
Requires-Dist: datasets
Requires-Dist: deepspeed>=0.18.2
Requires-Dist: devtools
Requires-Dist: jsonlines
Requires-Dist: loguru
Requires-Dist: nvidia-ml-py
Requires-Dist: openai>=1.48.0
Requires-Dist: peft
Requires-Dist: psutil
Requires-Dist: pydantic>=2.10
Requires-Dist: tabulate
Requires-Dist: torch
Requires-Dist: tqdm
Requires-Dist: transformers<5.0.0,>=4.56
Requires-Dist: wandb
Requires-Dist: yq
Provides-Extra: all
Requires-Dist: autodoc-pydantic>=2.0.0; extra == 'all'
Requires-Dist: autoflake; extra == 'all'
Requires-Dist: numba>=0.63; extra == 'all'
Requires-Dist: parameterized; extra == 'all'
Requires-Dist: pre-commit; extra == 'all'
Requires-Dist: pydantic>=2.0; extra == 'all'
Requires-Dist: pytest; extra == 'all'
Requires-Dist: pytest-instafail; extra == 'all'
Requires-Dist: pytest-xdist; extra == 'all'
Requires-Dist: snowflake-connector-python==3.12.3; extra == 'all'
Requires-Dist: snowflake-ml-python>=1.21.0; extra == 'all'
Requires-Dist: sphinx-autodoc-typehints; extra == 'all'
Requires-Dist: sphinx-copybutton; extra == 'all'
Requires-Dist: sphinx-rtd-theme; extra == 'all'
Requires-Dist: sphinx>=8.1.3; extra == 'all'
Requires-Dist: vllm==0.6.2; extra == 'all'
Provides-Extra: cortex
Requires-Dist: snowflake-connector-python==3.12.3; extra == 'cortex'
Provides-Extra: dev
Requires-Dist: autodoc-pydantic>=2.0.0; extra == 'dev'
Requires-Dist: autoflake; extra == 'dev'
Requires-Dist: numba>=0.63; extra == 'dev'
Requires-Dist: parameterized; extra == 'dev'
Requires-Dist: pre-commit; extra == 'dev'
Requires-Dist: pydantic>=2.0; extra == 'dev'
Requires-Dist: pytest; extra == 'dev'
Requires-Dist: pytest-instafail; extra == 'dev'
Requires-Dist: pytest-xdist; extra == 'dev'
Requires-Dist: snowflake-ml-python>=1.21.0; extra == 'dev'
Requires-Dist: sphinx-autodoc-typehints; extra == 'dev'
Requires-Dist: sphinx-copybutton; extra == 'dev'
Requires-Dist: sphinx-rtd-theme; extra == 'dev'
Requires-Dist: sphinx>=8.1.3; extra == 'dev'
Provides-Extra: docs
Requires-Dist: autodoc-pydantic>=2.0.0; extra == 'docs'
Requires-Dist: pydantic>=2.0; extra == 'docs'
Requires-Dist: sphinx-autodoc-typehints; extra == 'docs'
Requires-Dist: sphinx-copybutton; extra == 'docs'
Requires-Dist: sphinx-rtd-theme; extra == 'docs'
Requires-Dist: sphinx>=8.1.3; extra == 'docs'
Provides-Extra: formatting
Requires-Dist: autoflake; extra == 'formatting'
Requires-Dist: pre-commit; extra == 'formatting'
Provides-Extra: snowflake
Requires-Dist: numba>=0.63; extra == 'snowflake'
Requires-Dist: snowflake-ml-python>=1.21.0; extra == 'snowflake'
Provides-Extra: testing
Requires-Dist: numba>=0.63; extra == 'testing'
Requires-Dist: parameterized; extra == 'testing'
Requires-Dist: pytest; extra == 'testing'
Requires-Dist: pytest-instafail; extra == 'testing'
Requires-Dist: pytest-xdist; extra == 'testing'
Requires-Dist: snowflake-ml-python>=1.21.0; extra == 'testing'
Provides-Extra: vllm
Requires-Dist: vllm==0.6.2; extra == 'vllm'
